<?xml version="1.0" encoding="UTF-8"?>
<!-- Created with TexturePacker http://texturepacker.com-->
<!-- $TexturePacker:SmartUpdate:9522b68a01e6c9621c67d079bbc68ca6$ -->
<TextureAtlas imagePath="objectives-atlas@2x.pvr.gz">
    <SubTexture name="bookmark" x="399" y="216" width="64" height="64"/>
    <SubTexture name="caching-prompt" x="146" y="845" width="162" height="46"/>
    <SubTexture name="continue-button" x="2" y="788" width="168" height="56" frameX="0" frameY="-3" frameWidth="168" frameHeight="60"/>
    <SubTexture name="good-point" x="399" y="281" width="58" height="48"/>
    <SubTexture name="logbook" x="2" y="129" width="396" height="466" frameX="-4" frameY="-2" frameWidth="400" frameHeight="474"/>
    <SubTexture name="objectives-cross" x="464" y="249" width="32" height="32" frameX="-4" frameY="0" frameWidth="40" frameHeight="32"/>
    <SubTexture name="objectives-hat" x="259" y="596" width="183" height="146" frameX="0" frameY="-1" frameWidth="187" frameHeight="148"/>
    <SubTexture name="objectives-panel" x="2" y="2" width="476" height="126" frameX="-4" frameY="0" frameWidth="480" frameHeight="128"/>
    <SubTexture name="objectives-skull" x="399" y="129" width="110" height="86" frameX="0" frameY="-1" frameWidth="110" frameHeight="88"/>
    <SubTexture name="objectives-text" x="259" y="743" width="180" height="64"/>
    <SubTexture name="objectives-tick" x="464" y="216" width="38" height="32" frameX="-1" frameY="0" frameWidth="40" frameHeight="32"/>
    <SubTexture name="pause-quit-button" x="2" y="959" width="143" height="56" frameX="0" frameY="-3" frameWidth="143" frameHeight="60"/>
    <SubTexture name="pause-resume-button" x="2" y="902" width="143" height="56" frameX="0" frameY="-3" frameWidth="143" frameHeight="60"/>
    <SubTexture name="pause-retry-button" x="2" y="845" width="143" height="56" frameX="0" frameY="-3" frameWidth="143" frameHeight="60"/>
    <SubTexture name="pointer" x="458" y="282" width="50" height="176" frameX="-2" frameY="0" frameWidth="56" frameHeight="176"/>
    <SubTexture name="scroll-quarter-large" x="2" y="596" width="256" height="191"/>
</TextureAtlas>
